stac_fastapi/pgstac/__init__.py
stac_fastapi/pgstac/app.py
stac_fastapi/pgstac/config.py
stac_fastapi/pgstac/core.py
stac_fastapi/pgstac/db.py
stac_fastapi/pgstac/transactions.py
stac_fastapi/pgstac/utils.py
stac_fastapi/pgstac/version.py
stac_fastapi/pgstac/extensions/__init__.py
stac_fastapi/pgstac/extensions/filter.py
stac_fastapi/pgstac/extensions/free_text.py
stac_fastapi/pgstac/extensions/query.py
stac_fastapi/pgstac/models/__init__.py
stac_fastapi/pgstac/models/links.py
stac_fastapi/pgstac/types/base_item_cache.py
stac_fastapi/pgstac/types/search.py
stac_fastapi_pgstac-6.2.1.dist-info/METADATA
stac_fastapi_pgstac-6.2.1.dist-info/WHEEL
stac_fastapi_pgstac-6.2.1.dist-info/licenses/LICENSE
stac_fastapi_pgstac-6.2.1.dist-info/RECORD
