Metadata-Version: 2.4
Name: stac-fastapi-pgstac
Version: 6.2.1
Summary: An implementation of STAC API based on the FastAPI framework and using the pgstac backend.
Project-URL: Homepage, https://github.com/stac-utils/stac-fastapi-pgstac
Author-email: David Bitner <david@developmentseed.org>
Maintainer-email: David Bitner <david@developmentseed.org>, Vincent Sarago <vincent@developmentseed.org>, Pete Gadomski <pete.gadomski@gmail.com>, Henry Rodman <henry@developmentseed.org>, Jeff Albrecht <geospatialjeff@gmail.com>
License-Expression: MIT
License-File: LICENSE
Keywords: FastAPI,PgSTAC,STAC,STAC-API
Classifier: Intended Audience :: Developers
Classifier: Intended Audience :: Information Technology
Classifier: Intended Audience :: Science/Research
Classifier: License :: OSI Approved :: MIT License
Classifier: Programming Language :: Python :: 3.11
Classifier: Programming Language :: Python :: 3.12
Classifier: Programming Language :: Python :: 3.13
Classifier: Programming Language :: Python :: 3.14
Requires-Python: >=3.11
Requires-Dist: asyncpg
Requires-Dist: attrs
Requires-Dist: brotli-asgi
Requires-Dist: buildpg
Requires-Dist: cql2>=0.3.6
Requires-Dist: hydraters>=0.1.3
Requires-Dist: json-merge-patch>=0.3.0
Requires-Dist: jsonpatch>=1.33.0
Requires-Dist: orjson
Requires-Dist: pydantic-settings<3.0,>=2.7
Requires-Dist: pydantic<3.0,>=2.4
Requires-Dist: stac-fastapi-api<7.0,>=6.1
Requires-Dist: stac-fastapi-extensions<7.0,>=6.1
Requires-Dist: stac-fastapi-types<7.0,>=6.1
Provides-Extra: server
Requires-Dist: uvicorn[standard]==0.38.0; extra == 'server'
Provides-Extra: validation
Requires-Dist: stac-pydantic[validation]; extra == 'validation'
